CHANGELOG.txt
LICENCE.txt
MANIFEST.in
README.txt
setup.py
ml_package/__init__.py
ml_package.egg-info/PKG-INFO
ml_package.egg-info/SOURCES.txt
ml_package.egg-info/dependency_links.txt
ml_package.egg-info/requires.txt
ml_package.egg-info/top_level.txt