Metadata-Version: 1.1
Name: ml-package
Version: 0.0.4
Summary: Everything required for a ml project
Home-page: UNKNOWN
Author: Bharat Anand
Author-email: bharat3214@gmail.com
License: MIT
Keywords: ml
Platform: UNKNOWN
Classifier: Development Status :: 5 - Production/Stable
Classifier: Intended Audience :: Education
Classifier: Operating System :: Microsoft :: Windows :: Windows 10
Classifier: License :: OSI Approved :: MIT License
Classifier: Programming Language :: Python :: 3
